[
  {
    "id": "6676aa51-8fc1-45fa-8d08-29bf5fbd62d2",
    "duration": 1000,
    "league": "MotoGP Italy 2025",
    "icon": "https://i.imgur.com/hYCzOBd.png",
    "team1": {
      "name": "MotoGP",
      "logo": "https://i.imgur.com/enF2GWY.png"
    },
    "team2": {
      "name": "MotoGP",
      "logo": "https://i.imgur.com/enF2GWY.png"
    },
    "kickoff_date": "2025-06-20",
    "kickoff_time": "14:00",
    "match_date": "2025-06-20",
    "match_time": "14:00",
    "infogp": "Practice | 20:00 WIB", "firstRow": 3
  },
  {
    "id": "30c38818-1263-4ac3-ab3c-f6f37dde75bb",
    "duration": 3,
    "league": "Women's Volleyball Nations League",
    "icon": "https://i.imgur.com/HzZe9uC.png",
    "team1": {
      "name": "Bulgaria",
      "logo": "https://ssl.gstatic.com/onebox/media/sports/logos/iGHMbfNfFYBxRwqi_v8L3w_96x96.png"
    },
    "team2": {
      "name": "Czech Republic",
      "logo": "https://ssl.gstatic.com/onebox/media/sports/logos/8AluO-WxpcHtC0KKHmFgvg_96x96.png"
    },
    "kickoff_date": "2025-06-20",
    "kickoff_time": "16:00",
    "match_date": "2025-06-20",
    "match_time": "16:00",
    "infogp": "", "firstRow": 4
  },
  {
    "id": "9b597929-cfd3-46ea-b085-c232a723ca57",
    "duration": 3,
    "league": "Women's Volleyball Nations League",
    "icon": "https://i.imgur.com/HzZe9uC.png",
    "team1": {
      "name": "Japan",
      "logo": "https://ssl.gstatic.com/onebox/media/sports/logos/by4OltvtZz7taxuQtkiP3A_96x96.png"
    },
    "team2": {
      "name": "Italy",
      "logo": "https://ssl.gstatic.com/onebox/media/sports/logos/joYpsiaYi4GDCqhSRAq5Zg_96x96.png"
    },
    "kickoff_date": "2025-06-20",
    "kickoff_time": "19:30",
    "match_date": "2025-06-20",
    "match_time": "19:30",
    "infogp": "", "firstRow": 5
  },
  {
    "id": "85cd006c-be0b-4021-bf1a-a9ed594806eb",
    "duration": 3,
    "league": "Women's Volleyball Nations League",
    "icon": "https://i.imgur.com/HzZe9uC.png",
    "team1": {
      "name": "South Korea",
      "logo": "https://ssl.gstatic.com/onebox/media/sports/logos/Uu5pwNmMHGd5bCooKrS3Lw_96x96.png"
    },
    "team2": {
      "name": "Belgium",
      "logo": "https://ssl.gstatic.com/onebox/media/sports/logos/6SF7yEoB60bU5knw-M7R5Q_96x96.png"
    },
    "kickoff_date": "2025-06-20",
    "kickoff_time": "20:00",
    "match_date": "2025-06-20",
    "match_time": "20:00",
    "infogp": "", "firstRow": 6
  },
  {
    "id": "4e94fcbe-47d0-4ebd-a29f-63af0b0415db",
    "duration": 3,
    "league": "Women's Volleyball Nations League",
    "icon": "https://i.imgur.com/HzZe9uC.png",
    "team1": {
      "name": "France",
      "logo": "https://ssl.gstatic.com/onebox/media/sports/logos/z3JEQB3coEAGLCJBEUzQ2A_96x96.png"
    },
    "team2": {
      "name": "Netherlands",
      "logo": "https://ssl.gstatic.com/onebox/media/sports/logos/8GEqzfLegwFFpe6X2BODTg_96x96.png"
    },
    "kickoff_date": "2025-06-20",
    "kickoff_time": "21:30",
    "match_date": "2025-06-20",
    "match_time": "21:30",
    "infogp": "", "firstRow": 7
  },
  {
    "id": "3e30fa22-257c-4877-aad5-98680534f87c",
    "duration": 3,
    "league": "FIFA Club World Cup",
    "icon": "https://i.imgur.com/oJfBO55.png",
    "team1": {
      "name": "Benfica",
      "logo": "https://ssl.gstatic.com/onebox/media/sports/logos/nFwABZ-4n_A3BGXT9A7Adg_96x96.png"
    },
    "team2": {
      "name": "Auckland City",
      "logo": "https://ssl.gstatic.com/onebox/media/sports/logos/p_QnXPAoy8lpWCMGjvbkVg_96x96.png"
    },
    "kickoff_date": "2025-06-20",
    "kickoff_time": "23:00",
    "match_date": "2025-06-20",
    "match_time": "22:30",
    "infogp": "", "firstRow": 8
  },
  {
    "id": "8027ad85-7ec3-49c2-b9e6-2903cbc1b8c0",
    "duration": 3,
    "league": "Women's Volleyball Nations League",
    "icon": "https://i.imgur.com/HzZe9uC.png",
    "team1": {
      "name": "Canada",
      "logo": "https://ssl.gstatic.com/onebox/media/sports/logos/H23oIEP6qK-zNc3O8abnIA_96x96.png"
    },
    "team2": {
      "name": "Brazil",
      "logo": "https://ssl.gstatic.com/onebox/media/sports/logos/zKLzoJVYz0bb6oAnPUdwWQ_96x96.png"
    },
    "kickoff_date": "2025-06-20",
    "kickoff_time": "23:30",
    "match_date": "2025-06-20",
    "match_time": "23:30",
    "infogp": "", "firstRow": 9
  },
  {
    "id": "87d80efd-6580-430a-9de3-5f1aebf9c160",
    "duration": 2.17,
    "league": "UEFA U19 European Championship",
    "icon": "https://i.imgur.com/oJfBO55.png",
    "team1": {
      "name": "Norway U19",
      "logo": "https://ssl.gstatic.com/onebox/media/sports/logos/lLDKax72TPgU_Hcj0W-DOg_96x96.png"
    },
    "team2": {
      "name": "Germany U19",
      "logo": "https://ssl.gstatic.com/onebox/media/sports/logos/h1FhPLmDg9AHXzhygqvVPg_96x96.png"
    },
    "kickoff_date": "2025-06-21",
    "kickoff_time": "00:00",
    "match_date": "2025-06-21",
    "match_time": "00:00",
    "infogp": "", "firstRow": 10
  },
  {
    "id": "58bb6181-7059-4fb9-b5a4-6558af111c02",
    "duration": 2.17,
    "league": "UEFA U19 European Championship",
    "icon": "https://i.imgur.com/oJfBO55.png",
    "team1": {
      "name": "Netherlands U19",
      "logo": "https://ssl.gstatic.com/onebox/media/sports/logos/8GEqzfLegwFFpe6X2BODTg_96x96.png"
    },
    "team2": {
      "name": "England U19",
      "logo": "https://ssl.gstatic.com/onebox/media/sports/logos/DTqIL8Ba3KIuxGkpXw5ayA_96x96.png"
    },
    "kickoff_date": "2025-06-21",
    "kickoff_time": "00:00",
    "match_date": "2025-06-21",
    "match_time": "00:00",
    "infogp": "", "firstRow": 11
  },
  {
    "id": "d18f62bb-56f0-45c1-8ad4-b39e241131ce",
    "duration": 3,
    "league": "Women's Volleyball Nations League",
    "icon": "https://i.imgur.com/HzZe9uC.png",
    "team1": {
      "name": "Germany",
      "logo": "https://ssl.gstatic.com/onebox/media/sports/logos/h1FhPLmDg9AHXzhygqvVPg_96x96.png"
    },
    "team2": {
      "name": "Poland",
      "logo": "https://ssl.gstatic.com/onebox/media/sports/logos/yTS_Piy3M1wUBnqU0n5aAw_96x96.png"
    },
    "kickoff_date": "2025-06-21",
    "kickoff_time": "01:00",
    "match_date": "2025-06-21",
    "match_time": "01:00",
    "infogp": "", "firstRow": 12
  },
  {
    "id": "5ae69df6-87c0-4414-841b-f0955dcaef20",
    "duration": 3,
    "league": "FIFA Club World Cup",
    "icon": "https://i.imgur.com/oJfBO55.png",
    "team1": {
      "name": "Flamengo",
      "logo": "https://ssl.gstatic.com/onebox/media/sports/logos/orE554NToSkH6nuwofe7Yg_96x96.png"
    },
    "team2": {
      "name": "Chelsea",
      "logo": "https://ssl.gstatic.com/onebox/media/sports/logos/fhBITrIlbQxhVB6IjxUO6Q_96x96.png"
    },
    "kickoff_date": "2025-06-21",
    "kickoff_time": "01:00",
    "match_date": "2025-06-21",
    "match_time": "00:30",
    "infogp": "", "firstRow": 13
  },
  {
    "id": "ad7e8b7b-56f9-44d5-ab41-f37a0a71d7dc",
    "duration": 3,
    "league": "FIFA Club World Cup",
    "icon": "https://i.imgur.com/oJfBO55.png",
    "team1": {
      "name": "Los Angeles FC",
      "logo": "https://ssl.gstatic.com/onebox/media/sports/logos/waD0z1CWx6_r4UT_hgb7nA_96x96.png"
    },
    "team2": {
      "name": "ES Tunis",
      "logo": "https://ssl.gstatic.com/onebox/media/sports/logos/Kf32x8gh5SCMEqvKjVGLfg_96x96.png"
    },
    "kickoff_date": "2025-06-21",
    "kickoff_time": "05:00",
    "match_date": "2025-06-21",
    "match_time": "04:30",
    "infogp": "", "firstRow": 14
  },
  {
    "id": "ce56df14-acf0-4a53-8f70-15dfe56b2556",
    "duration": 3,
    "league": "FIFA Club World Cup",
    "icon": "https://i.imgur.com/oJfBO55.png",
    "team1": {
      "name": "Bayern Munchen",
      "logo": "https://ssl.gstatic.com/onebox/media/sports/logos/-_cmntP5q_pHL7g5LfkRiw_96x96.png"
    },
    "team2": {
      "name": "Boca Juniors",
      "logo": "https://ssl.gstatic.com/onebox/media/sports/logos/YO1impuFJT2hex6wvCd9Pw_96x96.png"
    },
    "kickoff_date": "2025-06-21",
    "kickoff_time": "08:00",
    "match_date": "2025-06-21",
    "match_time": "07:30",
    "infogp": "", "firstRow": 15
  }
]
