[
  {
    "id": "ecda1aed-8e7d-4457-823b-bf9842ab07f2",
    "servers": [
      {
        "key": "MxZCFVhaAg",
        "url": "https://bikinbaru94.blogspot.com/p/playermpdd.html?id=unifi11",
        "label": "HD AUTO"
      },
      {
        "key": "1te77yrhxs",
        "url": "https://bikinbaru94.blogspot.com/p/playermpdd.html?id=starzplay",
        "label": "HD AUTO"
      },
      {
        "key": "92j7dntwxc",
        "url": "",
        "label": "SD [IOS]"
      }
    ]
  },
  {
    "id": "02921476-b516-4561-8835-c4d4bc6b8d9c",
    "servers": [
      {
        "key": "nmHf4cH10R",
        "url": "https://live.jiatianxiazhuangshi.com/live/58267293_8825a6cddfe150d3046cb65b8fd7969d_nsd.m3u8",
        "label": "ANDROID/PC"
      },
      {
        "key": "X8jZ6Jlve2",
        "url": "",
        "label": ""
      },
      {
        "key": "B1VA4pFsxH",
        "url": "",
        "label": ""
      }
    ]
  },
  {
    "id": "5a642c5b-254c-4f9d-8a25-5f8ee1820695",
    "servers": [
      {
        "key": "XgGPZ1kV1N",
        "url": "https://vt-osoi7r4b.sportcdn.live/live/live-2-3853020-2.m3u8?txSecret=85a8e2418d72d2ac5be7874c1169f98b&txTime=682ea1a9",
        "label": "SD [IOS]"
      },
      {
        "key": "Lpq3OFjcBJ",
        "url": "",
        "label": ""
      },
      {
        "key": "laG0uCUZCI",
        "url": "",
        "label": ""
      }
    ]
  },
  {
    "id": "027cbda2-8044-4f68-a561-211e112b4540",
    "servers": [
      {
        "key": "rGWsW0DsVR",
        "url": "https://hlslive-tx-cdn.ysp.cctv.cn/peacetv/2027303601.m3u8",
        "label": "COURT 1"
      },
      {
        "key": "5Mpl4MyHDQ",
        "url": "https://hlslive-tx-cdn.ysp.cctv.cn/peacetv/2027302901.m3u8",
        "label": "COURT 2"
      },
      {
        "key": "iaoG1O1sBt",
        "url": "https://hlslive-tx-cdn.ysp.cctv.cn/peacetv/2027303701.m3u8",
        "label": "COURT 3"
      },
      {
        "key": "KkzhmttIgQ",
        "url": "https://hlslive-tx-cdn.ysp.cctv.cn/peacetv/2027303901.m3u8",
        "label": "COURT 4"
      },
      {
        "key": "05R2qPkq6w",
        "url": "https://bikinbaru94.blogspot.com/p/playermpdd.html?id=astro_bad1b",
        "label": "HD COURT 1"
      }
    ]
  }
]
